{
    "created_time": "2020-10-05T02:03:29Z",
    "files": [
        {
            "attachment_folder": "",
            "attachments": [
            ],
            "created_time": "2020-10-05T02:03:42Z",
            "modified_time": "2020-10-07T13:47:56Z",
            "name": "Linux_基础知识.md",
            "tags": [
            ]
        },
        {
            "attachment_folder": "",
            "attachments": [
            ],
            "created_time": "2020-10-07T13:49:29Z",
            "modified_time": "2020-10-07T13:58:00Z",
            "name": "Linux_安装MYSQL.md",
            "tags": [
            ]
        }
    ],
    "sub_directories": [
    ],
    "version": "1"
}
